SerDes_Labs/Lab1_Parallel_vs_Serial/Parallel_TxRx/parallel_rx.sv
`timescale 1ns/1ps

module parallel_rx #(parameter int WIDTH = 8)
(
    input  logic             rx_clk,
    input  logic             rst,
    input  logic [WIDTH-1:0] parallel_pins,
    output logic [WIDTH-1:0] data_out,
    output logic             data_valid
);

    always_ff @(negedge rx_clk) begin
        if (rst) begin
            data_out   <= '0;
            data_valid <= 1'b0;
        end else begin
            data_out   <= parallel_pins;
            data_valid <= 1'b1;
        end
    end

endmodule

SerDes_Labs/Lab1_Parallel_vs_Serial/Parallel_TxRx/parallel_tx.sv
`timescale 1ns/1ps

module parallel_tx #(parameter int WIDTH = 8)
(
    input  logic             tx_clk,
    input  logic             rst,
    input  logic [WIDTH-1:0] data_in,
    output logic [WIDTH-1:0] parallel_pins
);

    always_ff @(posedge tx_clk) begin
        if (rst)
            parallel_pins <= '0;
        else
            parallel_pins <= data_in;
    end

endmodule

SerDes_Labs/Lab1_Parallel_vs_Serial/Parallel_TxRx/top_level_parallel.sv
`timescale 1ns/1ps

module top_level_parallel #(
    parameter int WIDTH = 8
) (
    input  logic             CLK,
    input  logic             RST,
    input  logic [WIDTH-1:0] in_data,
    output logic [WIDTH-1:0] out_data,
    output logic VALID
);

    logic [WIDTH-1:0] transit_data;

    parallel_tx #(.WIDTH(WIDTH)) test_parallel_tx (
        .tx_clk       (CLK),
        .rst          (RST),
        .data_in      (in_data),
        .parallel_pins(transit_data)
    );

    parallel_rx #(.WIDTH(WIDTH)) test_parallel_rx (
        .rx_clk       (CLK),
        .rst          (RST),
        .parallel_pins(transit_data),
        .data_out     (out_data),
        .data_valid   (VALID)
    );

endmodule

SerDes_Labs/Lab1_Parallel_vs_Serial/Parallel_TxRx/tb_top_level_parallel.sv
`timescale 1ns/1ps

module tb_top_level_parallel;

    localparam int WIDTH = 8;

    logic             CLK;
    logic             RST;
    logic [WIDTH-1:0] in_data;
    logic [WIDTH-1:0] out_data;
    logic             VALID;

    int tests_passed;
    int tests_failed;

     initial begin
        $dumpfile("wave.vcd");
        $dumpvars(0, tb_top_level_parallel);
    end

    top_level_parallel #(
        .WIDTH(WIDTH)
    ) dut (
        .CLK     (CLK),
        .RST     (RST),
        .in_data (in_data),
        .out_data(out_data),
        .VALID   (VALID)
    );

    // 100 MHz clock:
    // Period = 10 ns
    always #5ns CLK <= ~CLK;

    task automatic send_and_check(
        input logic [WIDTH-1:0] test_value
    );
        begin
            /*
             * Falling edge:
             * Apply the next input word.
             *
             * Rising edge:
             * parallel_tx captures in_data.
             *
             * Following falling edge:
             * parallel_rx captures transit_data and asserts VALID.
             */

            @(negedge CLK);
            in_data = test_value;

            @(posedge CLK);
            @(negedge CLK);

            // Allow nonblocking assignments in parallel_rx to complete.
            #1ns;

            if (VALID !== 1'b1) begin
                $error(
                    "FAIL: VALID was not asserted for input 0x%02h",
                    test_value
                );

                tests_failed++;
            end
            else if (out_data !== test_value) begin
                $error(
                    "FAIL: sent 0x%02h, received 0x%02h",
                    test_value,
                    out_data
                );

                tests_failed++;
            end
            else begin
                $display(
                    "PASS: VALID=%b, sent 0x%02h, received 0x%02h",
                    VALID,
                    test_value,
                    out_data
                );

                tests_passed++;
            end
        end
    endtask

    initial begin
        CLK          = 1'b0;
        RST          = 1'b1;
        in_data      = '0;
        tests_passed = 0;
        tests_failed = 0;

        /*
         * The receiver resets on a falling edge, so wait for one before
         * checking its reset outputs.
         */
        @(negedge CLK);
        #1ns;

        if (VALID !== 1'b0) begin
            $error(
                "FAIL: VALID should be 0 during reset, but was %b",
                VALID
            );

            tests_failed++;
        end
        else begin
            $display("PASS: VALID is 0 during reset.");
            tests_passed++;
        end

        if (out_data !== '0) begin
            $error(
                "FAIL: out_data should be 0 during reset, but was 0x%02h",
                out_data
            );

            tests_failed++;
        end
        else begin
            $display("PASS: out_data is 0 during reset.");
            tests_passed++;
        end

        // Keep reset active for a few additional clock cycles.
        repeat (2) @(posedge CLK);

        // Deassert reset away from the TX rising edge.
        @(negedge CLK);
        RST = 1'b0;

        send_and_check(8'h00);
        send_and_check(8'h01);
        send_and_check(8'h55);
        send_and_check(8'hAA);
        send_and_check(8'hA5);
        send_and_check(8'h5A);
        send_and_check(8'hFF);

        // Test additional random values.
        repeat (20) begin
            send_and_check(
                WIDTH'($urandom())
            );
        end

        $display("--------------------------------");
        $display("Tests passed: %0d", tests_passed);
        $display("Tests failed: %0d", tests_failed);
        $display("--------------------------------");

        if (tests_failed == 0) begin
            $display("LAB 1 PARALLEL LINK TEST PASSED");
        end
        else begin
            $fatal(
                1,
                "LAB 1 PARALLEL LINK TEST FAILED WITH %0d ERROR(S)",
                tests_failed
            );
        end

        $finish;
    end

    // Prevent an endless simulation.
    initial begin
        #10us;
        $fatal(1, "Simulation timeout");
    end

endmodule

SerDes_Labs/Lab1_Parallel_vs_Serial/Parallel_TxRx/wave.vcd
$date
	Thu Jul 23 23:40:48 2026
$end
$version
	Icarus Verilog
$end
$timescale
	1ps
$end
$scope module tb_top_level_parallel $end
$var wire 8 ! out_data [7:0] $end
$var wire 1 " VALID $end
$var parameter 32 # WIDTH $end
$var reg 1 $ CLK $end
$var reg 1 % RST $end
$var reg 8 & in_data [7:0] $end
$var integer 32 ' tests_failed [31:0] $end
$var integer 32 ( tests_passed [31:0] $end
$scope module dut $end
$var wire 1 $ CLK $end
$var wire 1 % RST $end
$var wire 8 ) in_data [7:0] $end
$var wire 8 * transit_data [7:0] $end
$var wire 8 + out_data [7:0] $end
$var wire 1 " VALID $end
$var parameter 32 , WIDTH $end
$scope module test_parallel_rx $end
$var wire 1 % rst $end
$var wire 1 $ rx_clk $end
$var wire 8 - parallel_pins [7:0] $end
$var parameter 32 . WIDTH $end
$var reg 8 / data_out [7:0] $end
$var reg 1 " data_valid $end
$upscope $end
$scope module test_parallel_tx $end
$var wire 8 0 data_in [7:0] $end
$var wire 1 % rst $end
$var wire 1 $ tx_clk $end
$var parameter 32 1 WIDTH $end
$var reg 8 2 parallel_pins [7:0] $end
$upscope $end
$upscope $end
$scope task send_and_check $end
$upscope $end
$upscope $end
$enddefinitions $end
$comment Show the parameter values. $end
$dumpall
b1000 1
b1000 .
b1000 ,
b1000 #
$end
#0
$dumpvars
bx 2
b0 0
b0 /
bx -
b0 +
bx *
b0 )
b0 (
b0 '
b0 &
1%
0$
0"
b0 !
$end
#5000
b0 *
b0 -
b0 2
1$
#10000
0$
#11000
b10 (
#15000
1$
#20000
0$
#25000
1$
#30000
1"
0%
0$
#35000
1$
#40000
0$
#45000
1$
#50000
0$
#51000
b11 (
#55000
1$
#60000
b1 &
b1 )
b1 0
0$
#65000
b1 *
b1 -
b1 2
1$
#70000
b1 !
b1 +
b1 /
0$
#71000
b100 (
#75000
1$
#80000
b1010101 &
b1010101 )
b1010101 0
0$
#85000
b1010101 *
b1010101 -
b1010101 2
1$
#90000
b1010101 !
b1010101 +
b1010101 /
0$
#91000
b101 (
#95000
1$
#100000
b10101010 &
b10101010 )
b10101010 0
0$
#105000
b10101010 *
b10101010 -
b10101010 2
1$
#110000
b10101010 !
b10101010 +
b10101010 /
0$
#111000
b110 (
#115000
1$
#120000
b10100101 &
b10100101 )
b10100101 0
0$
#125000
b10100101 *
b10100101 -
b10100101 2
1$
#130000
b10100101 !
b10100101 +
b10100101 /
0$
#131000
b111 (
#135000
1$
#140000
b1011010 &
b1011010 )
b1011010 0
0$
#145000
b1011010 *
b1011010 -
b1011010 2
1$
#150000
b1011010 !
b1011010 +
b1011010 /
0$
#151000
b1000 (
#155000
1$
#160000
b11111111 &
b11111111 )
b11111111 0
0$
#165000
b11111111 *
b11111111 -
b11111111 2
1$
#170000
b11111111 !
b11111111 +
b11111111 /
0$
#171000
b1001 (
#175000
1$
#180000
b100100 &
b100100 )
b100100 0
0$
#185000
b100100 *
b100100 -
b100100 2
1$
#190000
b100100 !
b100100 +
b100100 /
0$
#191000
b1010 (
#195000
1$
#200000
b10000001 &
b10000001 )
b10000001 0
0$
#205000
b10000001 *
b10000001 -
b10000001 2
1$
#210000
b10000001 !
b10000001 +
b10000001 /
0$
#211000
b1011 (
#215000
1$
#220000
b1001 &
b1001 )
b1001 0
0$
#225000
b1001 *
b1001 -
b1001 2
1$
#230000
b1001 !
b1001 +
b1001 /
0$
#231000
b1100 (
#235000
1$
#240000
b1100011 &
b1100011 )
b1100011 0
0$
#245000
b1100011 *
b1100011 -
b1100011 2
1$
#250000
b1100011 !
b1100011 +
b1100011 /
0$
#251000
b1101 (
#255000
1$
#260000
b1101 &
b1101 )
b1101 0
0$
#265000
b1101 *
b1101 -
b1101 2
1$
#270000
b1101 !
b1101 +
b1101 /
0$
#271000
b1110 (
#275000
1$
#280000
b10001101 &
b10001101 )
b10001101 0
0$
#285000
b10001101 *
b10001101 -
b10001101 2
1$
#290000
b10001101 !
b10001101 +
b10001101 /
0$
#291000
b1111 (
#295000
1$
#300000
b1100101 &
b1100101 )
b1100101 0
0$
#305000
b1100101 *
b1100101 -
b1100101 2
1$
#310000
b1100101 !
b1100101 +
b1100101 /
0$
#311000
b10000 (
#315000
1$
#320000
b10010 &
b10010 )
b10010 0
0$
#325000
b10010 *
b10010 -
b10010 2
1$
#330000
b10010 !
b10010 +
b10010 /
0$
#331000
b10001 (
#335000
1$
#340000
b1 &
b1 )
b1 0
0$
#345000
b1 *
b1 -
b1 2
1$
#350000
b1 !
b1 +
b1 /
0$
#351000
b10010 (
#355000
1$
#360000
b1101 &
b1101 )
b1101 0
0$
#365000
b1101 *
b1101 -
b1101 2
1$
#370000
b1101 !
b1101 +
b1101 /
0$
#371000
b10011 (
#375000
1$
#380000
b1110110 &
b1110110 )
b1110110 0
0$
#385000
b1110110 *
b1110110 -
b1110110 2
1$
#390000
b1110110 !
b1110110 +
b1110110 /
0$
#391000
b10100 (
#395000
1$
#400000
b111101 &
b111101 )
b111101 0
0$
#405000
b111101 *
b111101 -
b111101 2
1$
#410000
b111101 !
b111101 +
b111101 /
0$
#411000
b10101 (
#415000
1$
#420000
b11101101 &
b11101101 )
b11101101 0
0$
#425000
b11101101 *
b11101101 -
b11101101 2
1$
#430000
b11101101 !
b11101101 +
b11101101 /
0$
#431000
b10110 (
#435000
1$
#440000
b10001100 &
b10001100 )
b10001100 0
0$
#445000
b10001100 *
b10001100 -
b10001100 2
1$
#450000
b10001100 !
b10001100 +
b10001100 /
0$
#451000
b10111 (
#455000
1$
#460000
b11111001 &
b11111001 )
b11111001 0
0$
#465000
b11111001 *
b11111001 -
b11111001 2
1$
#470000
b11111001 !
b11111001 +
b11111001 /
0$
#471000
b11000 (
#475000
1$
#480000
b11000110 &
b11000110 )
b11000110 0
0$
#485000
b11000110 *
b11000110 -
b11000110 2
1$
#490000
b11000110 !
b11000110 +
b11000110 /
0$
#491000
b11001 (
#495000
1$
#500000
b11000101 &
b11000101 )
b11000101 0
0$
#505000
b11000101 *
b11000101 -
b11000101 2
1$
#510000
b11000101 !
b11000101 +
b11000101 /
0$
#511000
b11010 (
#515000
1$
#520000
b10101010 &
b10101010 )
b10101010 0
0$
#525000
b10101010 *
b10101010 -
b10101010 2
1$
#530000
b10101010 !
b10101010 +
b10101010 /
0$
#531000
b11011 (
#535000
1$
#540000
b11100101 &
b11100101 )
b11100101 0
0$
#545000
b11100101 *
b11100101 -
b11100101 2
1$
#550000
b11100101 !
b11100101 +
b11100101 /
0$
#551000
b11100 (
#555000
1$
#560000
b1110111 &
b1110111 )
b1110111 0
0$
#565000
b1110111 *
b1110111 -
b1110111 2
1$
#570000
b1110111 !
b1110111 +
b1110111 /
0$
#571000
b11101 (
