SerDes_Labs/Lab1_Parallel_vs_Serial/SerDes_TxRx/Deserializer_rx.sv
`timescale 1ns/1ps

module Deserializer_rx #(
    parameter int WIDTH = 8
) (
    input  logic             rx_clk,
    input  logic             rst,

    input  logic             in_bit,
    input  logic             serial_valid,

    output logic [WIDTH-1:0] parallel_data,
    output logic             VALID
);

    localparam int COUNTER_WIDTH =
        (WIDTH <= 1) ? 1 : $clog2(WIDTH);

    logic [WIDTH-1:0]         saved_data;
    logic [COUNTER_WIDTH-1:0] counter;
    logic word_complete;

    always_ff @(negedge rx_clk) begin
        if (rst) begin
            saved_data    <= '0;
            parallel_data <= '0;
            counter       <= '0;
            word_complete <= 1'b0;
            VALID         <= 1'b0;
        end
        else begin
            // VALID is normally low and pulses for one clock cycle.
            VALID <= 1'b0;

            /*
             * saved_data was completed on the previous falling edge.
             *
             * We copy it now because nonblocking assignments do not
             * update saved_data until after an always_ff block finishes.
             */
            if (word_complete) begin
                parallel_data <= saved_data;
                VALID         <= 1'b1;
                word_complete <= 1'b0;
            end

            /*
             * Sample one incoming serial bit.
             */
            else if (serial_valid) begin
                /*
                 * Right-shift the current contents and insert the new
                 * serial bit into the MSB.
                 *
                 * For WIDTH = 8:
                 *
                 * saved_data = in_bit a b c d e f g
                 */
                saved_data <= {
                    in_bit,
                    saved_data[WIDTH-1:1]
                };

                /*
                 * counter = 0 means the first bit.
                 * counter = WIDTH-1 means the final bit.
                 */
                if (counter == COUNTER_WIDTH'(WIDTH - 1)) begin
                    counter       <= '0;
                    word_complete <= 1'b1;
                end
                else begin
                    counter <= counter + 1'b1;
                end
            end
        end
    end

endmodule

SerDes_Labs/Lab1_Parallel_vs_Serial/SerDes_TxRx/Serializer_tx.sv
`timescale 1ns/1ps

module Serializer_tx #(
    parameter int WIDTH = 8
) (
    input  logic             tx_clk,
    input  logic             rst,
    input  logic             data_ready,
    input  logic [WIDTH-1:0] parallel_data,

    output logic             busy,
    output logic             out_bit
);

    localparam int COUNTER_WIDTH =
        (WIDTH <= 1) ? 1 : $clog2(WIDTH);

    logic [COUNTER_WIDTH-1:0] counter;
    logic [WIDTH-1:0]         loaded_data;

    // Send the least-significant bit first.
    assign out_bit = busy ? loaded_data[0] : 1'b0;

    always_ff @(posedge tx_clk) begin
        if (rst) begin
            loaded_data <= '0;
            counter     <= '0;
            busy        <= 1'b0;
        end
        else begin
            /*
             * Load a new parallel word only when the serializer
             * is currently idle.
             */
            if (data_ready && !busy) begin
                loaded_data <= parallel_data;
                counter     <= '0;
                busy        <= 1'b1;
            end

            /*
             * Shift one bit during each clock cycle.
             */
            else if (busy) begin
                if (counter == COUNTER_WIDTH'(WIDTH - 1)) begin
                    /*
                     * The final bit was presented during the
                     * clock cycle that just finished.
                     */
                    loaded_data <= '0;
                    counter     <= '0;
                    busy        <= 1'b0;
                end
                else begin
                    loaded_data <= loaded_data >> 1;
                    counter     <= counter + 1'b1;
                end
            end
        end
    end

endmodule

SerDes_Labs/Lab1_Parallel_vs_Serial/SerDes_TxRx/top_level_serdes.sv
`timescale 1ns/1ps

module top_level_serdes #(
    parameter int WIDTH = 8
) (
    input  logic             CLK,
    input  logic             RST,

    // Parallel transmitter-side interface
    input  logic             data_ready,
    input  logic [WIDTH-1:0] in_data,

    // Status and reconstructed receiver data
    output logic             busy,
    output logic             serial_data,
    output logic [WIDTH-1:0] out_data,
    output logic             VALID
);

    /*
     * One-bit serial connection between the transmitter
     * and receiver.
     *
     * serial_data is also exposed as an output so that it
     * can be viewed easily in GTKWave.
     */

    Serializer_tx #(
        .WIDTH(WIDTH)
    ) serializer_inst (
        .tx_clk       (CLK),
        .rst          (RST),
        .data_ready   (data_ready),
        .parallel_data(in_data),
        .busy         (busy),
        .out_bit      (serial_data)
    );

    /*
     * The serializer updates serial_data on rising edges.
     * The deserializer samples it on falling edges.
     *
     * busy remains high for the complete serialized word,
     * so it is used as serial_valid.
     */
    Deserializer_rx #(
        .WIDTH(WIDTH)
    ) deserializer_inst (
        .rx_clk       (CLK),
        .rst          (RST),
        .in_bit       (serial_data),
        .serial_valid (busy),
        .parallel_data(out_data),
        .VALID        (VALID)
    );

endmodule

SerDes_Labs/Lab1_Parallel_vs_Serial/SerDes_TxRx/tb_top_level_serdes.sv
`timescale 1ns/1ps

module tb_top_level_serdes;

    localparam int  WIDTH        = 8;
    localparam time CLOCK_PERIOD = 10ns;

    logic             CLK;
    logic             RST;
    logic             data_ready;
    logic [WIDTH-1:0] in_data;

    logic             busy;
    logic             serial_data;
    logic [WIDTH-1:0] out_data;
    logic             VALID;

    int tests_passed;
    int tests_failed;

    top_level_serdes #(
        .WIDTH(WIDTH)
    ) dut (
        .CLK        (CLK),
        .RST        (RST),
        .data_ready (data_ready),
        .in_data    (in_data),
        .busy       (busy),
        .serial_data(serial_data),
        .out_data   (out_data),
        .VALID      (VALID)
    );

    /*
     * 100 MHz clock:
     *
     * Period = 10 ns
     */
    always #(CLOCK_PERIOD / 2) begin
        CLK <= ~CLK;
    end

    /*
     * Send one parallel word and verify the complete transfer.
     */
    task automatic send_and_check(
        input logic [WIDTH-1:0] test_value
    );

        logic transaction_failed;

        begin
            transaction_failed = 1'b0;

            /*
             * Wait until the serializer is idle.
             */
            wait (busy === 1'b0);

            /*
             * Apply the next word on a falling edge.
             *
             * This gives the input half a clock period of setup
             * time before the serializer captures it.
             */
            @(negedge CLK);

            in_data    = test_value;
            data_ready = 1'b1;

            /*
             * Serializer captures in_data on this rising edge.
             */
            @(posedge CLK);
            #1ns;

            data_ready = 1'b0;

            if (busy !== 1'b1) begin
                $error(
                    "FAIL: busy did not assert after loading 0x%0h",
                    test_value
                );

                transaction_failed = 1'b1;
            end

            /*
             * Check all WIDTH serial bits.
             *
             * The serializer sends:
             *
             * test_value[0], test_value[1], ..., test_value[WIDTH-1]
             *
             * The receiver samples each one on a falling edge.
             */
            for (
                int bit_index = 0;
                bit_index < WIDTH;
                bit_index++
            ) begin

                @(negedge CLK);
                #1ns;

                if (serial_data !== test_value[bit_index]) begin
                    $error(
                        "FAIL: word 0x%0h, bit %0d: expected %b, got %b",
                        test_value,
                        bit_index,
                        test_value[bit_index],
                        serial_data
                    );

                    transaction_failed = 1'b1;
                end

                /*
                 * With your word_complete implementation, VALID
                 * must remain low during all eight bit samples.
                 */
                if (VALID !== 1'b0) begin
                    $error(
                        "FAIL: VALID asserted too early while receiving ",
                        "bit %0d of word 0x%0h",
                        bit_index,
                        test_value
                    );

                    transaction_failed = 1'b1;
                end
            end

            /*
             * After the eighth falling edge, word_complete is set.
             *
             * On the following rising edge, the serializer clears busy.
             */
            @(posedge CLK);
            #1ns;

            if (busy !== 1'b0) begin
                $error(
                    "FAIL: busy did not clear after transmitting 0x%0h",
                    test_value
                );

                transaction_failed = 1'b1;
            end

            /*
             * On the following falling edge, the deserializer copies
             * saved_data into out_data and asserts VALID.
             */
            @(negedge CLK);
            #1ns;

            if (VALID !== 1'b1) begin
                $error(
                    "FAIL: VALID did not assert for word 0x%0h",
                    test_value
                );

                transaction_failed = 1'b1;
            end

            if (out_data !== test_value) begin
                $error(
                    "FAIL: sent 0x%0h, received 0x%0h",
                    test_value,
                    out_data
                );

                transaction_failed = 1'b1;
            end

            if (transaction_failed) begin
                tests_failed++;

                $display(
                    "TRANSACTION FAILED: sent 0x%0h, received 0x%0h",
                    test_value,
                    out_data
                );
            end
            else begin
                tests_passed++;

                $display(
                    "TRANSACTION PASSED: sent 0x%0h, received 0x%0h",
                    test_value,
                    out_data
                );
            end

            /*
             * VALID should return low on the next falling edge.
             */
            @(negedge CLK);
            #1ns;

            if (VALID !== 1'b0) begin
                $error(
                    "FAIL: VALID did not return low after word 0x%0h",
                    test_value
                );

                tests_failed++;
            end
        end

    endtask

    initial begin
        $dumpfile("wave.vcd");
        $dumpvars(0, tb_top_level_serdes);

        CLK          = 1'b0;
        RST          = 1'b1;
        data_ready   = 1'b0;
        in_data      = '0;
        tests_passed = 0;
        tests_failed = 0;

        /*
         * The serializer resets on a rising edge.
         * The deserializer resets on a falling edge.
         *
         * Keep reset active long enough for both.
         */
        repeat (3) @(posedge CLK);
        @(negedge CLK);
        #1ns;

        if (busy !== 1'b0) begin
            $error(
                "FAIL: busy should be 0 during reset, got %b",
                busy
            );

            tests_failed++;
        end

        if (VALID !== 1'b0) begin
            $error(
                "FAIL: VALID should be 0 during reset, got %b",
                VALID
            );

            tests_failed++;
        end

        if (serial_data !== 1'b0) begin
            $error(
                "FAIL: serial_data should be 0 during reset, got %b",
                serial_data
            );

            tests_failed++;
        end

        if (out_data !== '0) begin
            $error(
                "FAIL: out_data should be zero during reset, got 0x%0h",
                out_data
            );

            tests_failed++;
        end

        /*
         * Release reset on a falling edge, away from the
         * serializer's active rising edge.
         */
        RST = 1'b0;

        /*
         * Directed tests.
         */
        send_and_check(8'h00);
        send_and_check(8'h01);
        send_and_check(8'h80);
        send_and_check(8'h55);
        send_and_check(8'hAA);
        send_and_check(8'hA5);
        send_and_check(8'h5A);
        send_and_check(8'hFF);

        /*
         * Pseudorandom tests.
         */
        repeat (20) begin
            send_and_check(
                WIDTH'($urandom())
            );
        end

        $display("");
        $display("----------------------------------------");
        $display("LAB 1 SERIAL LINK TEST SUMMARY");
        $display("Transactions passed: %0d", tests_passed);
        $display("Errors detected:     %0d", tests_failed);
        $display("----------------------------------------");

        if (tests_failed == 0) begin
            $display("LAB 1 SERIAL LINK TEST PASSED");
        end
        else begin
            $fatal(
                1,
                "LAB 1 SERIAL LINK TEST FAILED WITH %0d ERROR(S)",
                tests_failed
            );
        end

        $finish;
    end

    /*
     * Simulation timeout in case the serializer or receiver
     * becomes stuck.
     */
    initial begin
        #100us;
        $fatal(1, "Simulation timeout");
    end

endmodule

SerDes_Labs/Lab1_Parallel_vs_Serial/SerDes_TxRx/wave.vcd
$date
	Fri Jul 24 01:26:07 2026
$end
$version
	Icarus Verilog
$end
$timescale
	1ps
$end
$scope module tb_top_level_serdes $end
$var wire 1 ! serial_data $end
$var wire 8 " out_data [7:0] $end
$var wire 1 # busy $end
$var wire 1 $ VALID $end
$var parameter 64 % CLOCK_PERIOD $end
$var parameter 32 & WIDTH $end
$var reg 1 ' CLK $end
$var reg 1 ( RST $end
$var reg 1 ) data_ready $end
$var reg 8 * in_data [7:0] $end
$var integer 32 + tests_failed [31:0] $end
$var integer 32 , tests_passed [31:0] $end
$scope module dut $end
$var wire 1 ' CLK $end
$var wire 1 ( RST $end
$var wire 1 ) data_ready $end
$var wire 8 - in_data [7:0] $end
$var wire 1 ! serial_data $end
$var wire 8 . out_data [7:0] $end
$var wire 1 # busy $end
$var wire 1 $ VALID $end
$var parameter 32 / WIDTH $end
$scope module deserializer_inst $end
$var wire 1 ( rst $end
$var wire 1 ' rx_clk $end
$var wire 1 # serial_valid $end
$var wire 1 ! in_bit $end
$var parameter 32 0 COUNTER_WIDTH $end
$var parameter 32 1 WIDTH $end
$var reg 1 $ VALID $end
$var reg 3 2 counter [2:0] $end
$var reg 8 3 parallel_data [7:0] $end
$var reg 8 4 saved_data [7:0] $end
$var reg 1 5 word_complete $end
$upscope $end
$scope module serializer_inst $end
$var wire 1 ) data_ready $end
$var wire 8 6 parallel_data [7:0] $end
$var wire 1 ( rst $end
$var wire 1 ' tx_clk $end
$var wire 1 ! out_bit $end
$var parameter 32 7 COUNTER_WIDTH $end
$var parameter 32 8 WIDTH $end
$var reg 1 # busy $end
$var reg 3 9 counter [2:0] $end
$var reg 8 : loaded_data [7:0] $end
$upscope $end
$upscope $end
$scope task send_and_check $end
$scope begin $ivl_for_loop0 $end
$upscope $end
$upscope $end
$upscope $end
$enddefinitions $end
$comment Show the parameter values. $end
$dumpall
b1000 8
b11 7
b1000 1
b11 0
b1000 /
b1000 &
b1010 %
$end
#0
$dumpvars
bx :
bx 9
b0 6
05
b0 4
b0 3
b0 2
b0 .
b0 -
b0 ,
b0 +
b0 *
0)
1(
0'
0$
x#
b0 "
x!
$end
#5000
0!
0#
b0 9
b0 :
1'
#10000
0'
#15000
1'
#20000
0'
#25000
1'
#30000
0'
#31000
0(
#35000
1'
#40000
1)
0'
#45000
1#
1'
#46000
0)
#50000
b1 2
0'
#55000
b1 9
1'
#60000
b10 2
0'
#65000
b10 9
1'
#70000
b11 2
0'
#75000
b11 9
1'
#80000
b100 2
0'
#85000
b100 9
1'
#90000
b101 2
0'
#95000
b101 9
1'
#100000
b110 2
0'
#105000
b110 9
1'
#110000
b111 2
0'
#115000
b111 9
1'
#120000
15
b0 2
0'
#125000
0#
b0 9
1'
#130000
05
1$
0'
#131000
b1 ,
#135000
1'
#140000
0$
0'
#145000
1'
#150000
1)
b1 *
b1 -
b1 6
0'
#155000
1!
1#
b1 :
1'
#156000
0)
#160000
b1 2
b10000000 4
0'
#165000
0!
b1 9
b0 :
1'
#170000
b10 2
b1000000 4
0'
#175000
b10 9
1'
#180000
b11 2
b100000 4
0'
#185000
b11 9
1'
#190000
b100 2
b10000 4
0'
#195000
b100 9
1'
#200000
b101 2
b1000 4
0'
#205000
b101 9
1'
#210000
b110 2
b100 4
0'
#215000
b110 9
1'
#220000
b111 2
b10 4
0'
#225000
b111 9
1'
#230000
15
b0 2
b1 4
0'
#235000
0#
b0 9
1'
#240000
05
1$
b1 "
b1 .
b1 3
0'
#241000
b10 ,
#245000
1'
#250000
0$
0'
#255000
1'
#260000
1)
b10000000 *
b10000000 -
b10000000 6
0'
#265000
1#
b10000000 :
1'
#266000
0)
#270000
b1 2
b0 4
0'
#275000
b1 9
b1000000 :
1'
#280000
b10 2
0'
#285000
b10 9
b100000 :
1'
#290000
b11 2
0'
#295000
b11 9
b10000 :
1'
#300000
b100 2
0'
#305000
b100 9
b1000 :
1'
#310000
b101 2
0'
#315000
b101 9
b100 :
1'
#320000
b110 2
0'
#325000
b110 9
b10 :
1'
#330000
b111 2
0'
#335000
1!
b111 9
b1 :
1'
#340000
15
b0 2
b10000000 4
0'
#345000
0!
0#
b0 9
b0 :
1'
#350000
05
1$
b10000000 "
b10000000 .
b10000000 3
0'
#351000
b11 ,
#355000
1'
#360000
0$
0'
#365000
1'
#370000
1)
b1010101 *
b1010101 -
b1010101 6
0'
#375000
1!
1#
b1010101 :
1'
#376000
0)
#380000
b1 2
b11000000 4
0'
#385000
0!
b1 9
b101010 :
1'
#390000
b10 2
b1100000 4
0'
#395000
1!
b10 9
b10101 :
1'
#400000
b11 2
b10110000 4
0'
#405000
0!
b11 9
b1010 :
1'
#410000
b100 2
b1011000 4
0'
#415000
1!
b100 9
b101 :
1'
#420000
b101 2
b10101100 4
0'
#425000
0!
b101 9
b10 :
1'
#430000
b110 2
b1010110 4
0'
#435000
1!
b110 9
b1 :
1'
#440000
b111 2
b10101011 4
0'
#445000
0!
b111 9
b0 :
1'
#450000
15
b0 2
b1010101 4
0'
#455000
0#
b0 9
1'
#460000
05
1$
b1010101 "
b1010101 .
b1010101 3
0'
#461000
b100 ,
#465000
1'
#470000
0$
0'
#475000
1'
#480000
1)
b10101010 *
b10101010 -
b10101010 6
0'
#485000
1#
b10101010 :
1'
#486000
0)
#490000
b1 2
b101010 4
0'
#495000
1!
b1 9
b1010101 :
1'
#500000
b10 2
b10010101 4
0'
#505000
0!
b10 9
b101010 :
1'
#510000
b11 2
b1001010 4
0'
#515000
1!
b11 9
b10101 :
1'
#520000
b100 2
b10100101 4
0'
#525000
0!
b100 9
b1010 :
1'
#530000
b101 2
b1010010 4
0'
#535000
1!
b101 9
b101 :
1'
#540000
b110 2
b10101001 4
0'
#545000
0!
b110 9
b10 :
1'
#550000
b111 2
b1010100 4
0'
#555000
1!
b111 9
b1 :
1'
#560000
15
b0 2
b10101010 4
0'
#565000
0!
0#
b0 9
b0 :
1'
#570000
05
1$
b10101010 "
b10101010 .
b10101010 3
0'
#571000
b101 ,
#575000
1'
#580000
0$
0'
#585000
1'
#590000
1)
b10100101 *
b10100101 -
b10100101 6
0'
#595000
1!
1#
b10100101 :
1'
#596000
0)
#600000
b1 2
b11010101 4
0'
#605000
0!
b1 9
b1010010 :
1'
#610000
b10 2
b1101010 4
0'
#615000
1!
b10 9
b101001 :
1'
#620000
b11 2
b10110101 4
0'
#625000
0!
b11 9
b10100 :
1'
#630000
b100 2
b1011010 4
0'
#635000
b100 9
b1010 :
1'
#640000
b101 2
b101101 4
0'
#645000
1!
b101 9
b101 :
1'
#650000
b110 2
b10010110 4
0'
#655000
0!
b110 9
b10 :
1'
#660000
b111 2
b1001011 4
0'
#665000
1!
b111 9
b1 :
1'
#670000
15
b0 2
b10100101 4
0'
#675000
0!
0#
b0 9
b0 :
1'
#680000
05
1$
b10100101 "
b10100101 .
b10100101 3
0'
#681000
b110 ,
#685000
1'
#690000
0$
0'
#695000
1'
#700000
1)
b1011010 *
b1011010 -
b1011010 6
0'
#705000
1#
b1011010 :
1'
#706000
0)
#710000
b1 2
b1010010 4
0'
#715000
1!
b1 9
b101101 :
1'
#720000
b10 2
b10101001 4
0'
#725000
0!
b10 9
b10110 :
1'
#730000
b11 2
b1010100 4
0'
#735000
1!
b11 9
b1011 :
1'
#740000
b100 2
b10101010 4
0'
#745000
b100 9
b101 :
1'
#750000
b101 2
b11010101 4
0'
#755000
0!
b101 9
b10 :
1'
#760000
b110 2
b1101010 4
0'
#765000
1!
b110 9
b1 :
1'
#770000
b111 2
b10110101 4
0'
#775000
0!
b111 9
b0 :
1'
#780000
15
b0 2
b1011010 4
0'
#785000
0#
b0 9
1'
#790000
05
1$
b1011010 "
b1011010 .
b1011010 3
0'
#791000
b111 ,
#795000
1'
#800000
0$
0'
#805000
1'
#810000
1)
b11111111 *
b11111111 -
b11111111 6
0'
#815000
1!
1#
b11111111 :
1'
#816000
0)
#820000
b1 2
b10101101 4
0'
#825000
b1 9
b1111111 :
1'
#830000
b10 2
b11010110 4
0'
#835000
b10 9
b111111 :
1'
#840000
b11 2
b11101011 4
0'
#845000
b11 9
b11111 :
1'
#850000
b100 2
b11110101 4
0'
#855000
b100 9
b1111 :
1'
#860000
b101 2
b11111010 4
0'
#865000
b101 9
b111 :
1'
#870000
b110 2
b11111101 4
0'
#875000
b110 9
b11 :
1'
#880000
b111 2
b11111110 4
0'
#885000
b111 9
b1 :
1'
#890000
15
b0 2
b11111111 4
0'
#895000
0!
0#
b0 9
b0 :
1'
#900000
05
1$
b11111111 "
b11111111 .
b11111111 3
0'
#901000
b1000 ,
#905000
1'
#910000
0$
0'
#915000
1'
#920000
1)
b100100 *
b100100 -
b100100 6
0'
#925000
1#
b100100 :
1'
#926000
0)
#930000
b1 2
b1111111 4
0'
#935000
b1 9
b10010 :
1'
#940000
b10 2
b111111 4
0'
#945000
1!
b10 9
b1001 :
1'
#950000
b11 2
b10011111 4
0'
#955000
0!
b11 9
b100 :
1'
#960000
b100 2
b1001111 4
0'
#965000
b100 9
b10 :
1'
#970000
b101 2
b100111 4
0'
#975000
1!
b101 9
b1 :
1'
#980000
b110 2
b10010011 4
0'
#985000
0!
b110 9
b0 :
1'
#990000
b111 2
b1001001 4
0'
#995000
b111 9
1'
#1000000
15
b0 2
b100100 4
0'
#1005000
0#
b0 9
1'
#1010000
05
1$
b100100 "
b100100 .
b100100 3
0'
#1011000
b1001 ,
#1015000
1'
#1020000
0$
0'
#1025000
1'
#1030000
1)
b10000001 *
b10000001 -
b10000001 6
0'
#1035000
1!
1#
b10000001 :
1'
#1036000
0)
#1040000
b1 2
b10010010 4
0'
#1045000
0!
b1 9
b1000000 :
1'
#1050000
b10 2
b1001001 4
0'
#1055000
b10 9
b100000 :
1'
#1060000
b11 2
b100100 4
0'
#1065000
b11 9
b10000 :
1'
#1070000
b100 2
b10010 4
0'
#1075000
b100 9
b1000 :
1'
#1080000
b101 2
b1001 4
0'
#1085000
b101 9
b100 :
1'
#1090000
b110 2
b100 4
0'
#1095000
b110 9
b10 :
1'
#1100000
b111 2
b10 4
0'
#1105000
1!
b111 9
b1 :
1'
#1110000
15
b0 2
b10000001 4
0'
#1115000
0!
0#
b0 9
b0 :
1'
#1120000
05
1$
b10000001 "
b10000001 .
b10000001 3
0'
#1121000
b1010 ,
#1125000
1'
#1130000
0$
0'
#1135000
1'
#1140000
1)
b1001 *
b1001 -
b1001 6
0'
#1145000
1!
1#
b1001 :
1'
#1146000
0)
#1150000
b1 2
b11000000 4
0'
#1155000
0!
b1 9
b100 :
1'
#1160000
b10 2
b1100000 4
0'
#1165000
b10 9
b10 :
1'
#1170000
b11 2
b110000 4
0'
#1175000
1!
b11 9
b1 :
1'
#1180000
b100 2
b10011000 4
0'
#1185000
0!
b100 9
b0 :
1'
#1190000
b101 2
b1001100 4
0'
#1195000
b101 9
1'
#1200000
b110 2
b100110 4
0'
#1205000
b110 9
1'
#1210000
b111 2
b10011 4
0'
#1215000
b111 9
1'
#1220000
15
b0 2
b1001 4
0'
#1225000
0#
b0 9
1'
#1230000
05
1$
b1001 "
b1001 .
b1001 3
0'
#1231000
b1011 ,
#1235000
1'
#1240000
0$
0'
#1245000
1'
#1250000
1)
b1100011 *
b1100011 -
b1100011 6
0'
#1255000
1!
1#
b1100011 :
1'
#1256000
0)
#1260000
b1 2
b10000100 4
0'
#1265000
b1 9
b110001 :
1'
#1270000
b10 2
b11000010 4
0'
#1275000
0!
b10 9
b11000 :
1'
#1280000
b11 2
b1100001 4
0'
#1285000
b11 9
b1100 :
1'
#1290000
b100 2
b110000 4
0'
#1295000
b100 9
b110 :
1'
#1300000
b101 2
b11000 4
0'
#1305000
1!
b101 9
b11 :
1'
#1310000
b110 2
b10001100 4
0'
#1315000
b110 9
b1 :
1'
#1320000
b111 2
b11000110 4
0'
#1325000
0!
b111 9
b0 :
1'
#1330000
15
b0 2
b1100011 4
0'
#1335000
0#
b0 9
1'
#1340000
05
1$
b1100011 "
b1100011 .
b1100011 3
0'
#1341000
b1100 ,
#1345000
1'
#1350000
0$
0'
#1355000
1'
#1360000
1)
b1101 *
b1101 -
b1101 6
0'
#1365000
1!
1#
b1101 :
1'
#1366000
0)
#1370000
b1 2
b10110001 4
0'
#1375000
0!
b1 9
b110 :
1'
#1380000
b10 2
b1011000 4
0'
#1385000
1!
b10 9
b11 :
1'
#1390000
b11 2
b10101100 4
0'
#1395000
b11 9
b1 :
1'
#1400000
b100 2
b11010110 4
0'
#1405000
0!
b100 9
b0 :
1'
#1410000
b101 2
b1101011 4
0'
#1415000
b101 9
1'
#1420000
b110 2
b110101 4
0'
#1425000
b110 9
1'
#1430000
b111 2
b11010 4
0'
#1435000
b111 9
1'
#1440000
15
b0 2
b1101 4
0'
#1445000
0#
b0 9
1'
#1450000
05
1$
b1101 "
b1101 .
b1101 3
0'
#1451000
b1101 ,
#1455000
1'
#1460000
0$
0'
#1465000
1'
#1470000
1)
b10001101 *
b10001101 -
b10001101 6
0'
#1475000
1!
1#
b10001101 :
1'
#1476000
0)
#1480000
b1 2
b10000110 4
0'
#1485000
0!
b1 9
b1000110 :
1'
#1490000
b10 2
b1000011 4
0'
#1495000
1!
b10 9
b100011 :
1'
#1500000
b11 2
b10100001 4
0'
#1505000
b11 9
b10001 :
1'
#1510000
b100 2
b11010000 4
0'
#1515000
0!
b100 9
b1000 :
1'
#1520000
b101 2
b1101000 4
0'
#1525000
b101 9
b100 :
1'
#1530000
b110 2
b110100 4
0'
#1535000
b110 9
b10 :
1'
#1540000
b111 2
b11010 4
0'
#1545000
1!
b111 9
b1 :
1'
#1550000
15
b0 2
b10001101 4
0'
#1555000
0!
0#
b0 9
b0 :
1'
#1560000
05
1$
b10001101 "
b10001101 .
b10001101 3
0'
#1561000
b1110 ,
#1565000
1'
#1570000
0$
0'
#1575000
1'
#1580000
1)
b1100101 *
b1100101 -
b1100101 6
0'
#1585000
1!
1#
b1100101 :
1'
#1586000
0)
#1590000
b1 2
b11000110 4
0'
#1595000
0!
b1 9
b110010 :
1'
#1600000
b10 2
b1100011 4
0'
#1605000
1!
b10 9
b11001 :
1'
#1610000
b11 2
b10110001 4
0'
#1615000
0!
b11 9
b1100 :
1'
#1620000
b100 2
b1011000 4
0'
#1625000
b100 9
b110 :
1'
#1630000
b101 2
b101100 4
0'
#1635000
1!
b101 9
b11 :
1'
#1640000
b110 2
b10010110 4
0'
#1645000
b110 9
b1 :
1'
#1650000
b111 2
b11001011 4
0'
#1655000
0!
b111 9
b0 :
1'
#1660000
15
b0 2
b1100101 4
0'
#1665000
0#
b0 9
1'
#1670000
05
1$
b1100101 "
b1100101 .
b1100101 3
0'
#1671000
b1111 ,
#1675000
1'
#1680000
0$
0'
#1685000
1'
#1690000
1)
b10010 *
b10010 -
b10010 6
0'
#1695000
1#
b10010 :
1'
#1696000
0)
#1700000
b1 2
b110010 4
0'
#1705000
1!
b1 9
b1001 :
1'
#1710000
b10 2
b10011001 4
0'
#1715000
0!
b10 9
b100 :
1'
#1720000
b11 2
b1001100 4
0'
#1725000
b11 9
b10 :
1'
#1730000
b100 2
b100110 4
0'
#1735000
1!
b100 9
b1 :
1'
#1740000
b101 2
b10010011 4
0'
#1745000
0!
b101 9
b0 :
1'
#1750000
b110 2
b1001001 4
0'
#1755000
b110 9
1'
#1760000
b111 2
b100100 4
0'
#1765000
b111 9
1'
#1770000
15
b0 2
b10010 4
0'
#1775000
0#
b0 9
1'
#1780000
05
1$
b10010 "
b10010 .
b10010 3
0'
#1781000
b10000 ,
#1785000
1'
#1790000
0$
0'
#1795000
1'
#1800000
1)
b1 *
b1 -
b1 6
0'
#1805000
1!
1#
b1 :
1'
#1806000
0)
#1810000
b1 2
b10001001 4
0'
#1815000
0!
b1 9
b0 :
1'
#1820000
b10 2
b1000100 4
0'
#1825000
b10 9
1'
#1830000
b11 2
b100010 4
0'
#1835000
b11 9
1'
#1840000
b100 2
b10001 4
0'
#1845000
b100 9
1'
#1850000
b101 2
b1000 4
0'
#1855000
b101 9
1'
#1860000
b110 2
b100 4
0'
#1865000
b110 9
1'
#1870000
b111 2
b10 4
0'
#1875000
b111 9
1'
#1880000
15
b0 2
b1 4
0'
#1885000
0#
b0 9
1'
#1890000
05
1$
b1 "
b1 .
b1 3
0'
#1891000
b10001 ,
#1895000
1'
#1900000
0$
0'
#1905000
1'
#1910000
1)
b1101 *
b1101 -
b1101 6
0'
#1915000
1!
1#
b1101 :
1'
#1916000
0)
#1920000
b1 2
b10000000 4
0'
#1925000
0!
b1 9
b110 :
1'
#1930000
b10 2
b1000000 4
0'
#1935000
1!
b10 9
b11 :
1'
#1940000
b11 2
b10100000 4
0'
#1945000
b11 9
b1 :
1'
#1950000
b100 2
b11010000 4
0'
#1955000
0!
b100 9
b0 :
1'
#1960000
b101 2
b1101000 4
0'
#1965000
b101 9
1'
#1970000
b110 2
b110100 4
0'
#1975000
b110 9
1'
#1980000
b111 2
b11010 4
0'
#1985000
b111 9
1'
#1990000
15
b0 2
b1101 4
0'
#1995000
0#
b0 9
1'
#2000000
05
1$
b1101 "
b1101 .
b1101 3
0'
#2001000
b10010 ,
#2005000
1'
#2010000
0$
0'
#2015000
1'
#2020000
1)
b1110110 *
b1110110 -
b1110110 6
0'
#2025000
1#
b1110110 :
1'
#2026000
0)
#2030000
b1 2
b110 4
0'
#2035000
1!
b1 9
b111011 :
1'
#2040000
b10 2
b10000011 4
0'
#2045000
b10 9
b11101 :
1'
#2050000
b11 2
b11000001 4
0'
#2055000
0!
b11 9
b1110 :
1'
#2060000
b100 2
b1100000 4
0'
#2065000
1!
b100 9
b111 :
1'
#2070000
b101 2
b10110000 4
0'
#2075000
b101 9
b11 :
1'
#2080000
b110 2
b11011000 4
0'
#2085000
b110 9
b1 :
1'
#2090000
b111 2
b11101100 4
0'
#2095000
0!
b111 9
b0 :
1'
#2100000
15
b0 2
b1110110 4
0'
#2105000
0#
b0 9
1'
#2110000
05
1$
b1110110 "
b1110110 .
b1110110 3
0'
#2111000
b10011 ,
#2115000
1'
#2120000
0$
0'
#2125000
1'
#2130000
1)
b111101 *
b111101 -
b111101 6
0'
#2135000
1!
1#
b111101 :
1'
#2136000
0)
#2140000
b1 2
b10111011 4
0'
#2145000
0!
b1 9
b11110 :
1'
#2150000
b10 2
b1011101 4
0'
#2155000
1!
b10 9
b1111 :
1'
#2160000
b11 2
b10101110 4
0'
#2165000
b11 9
b111 :
1'
#2170000
b100 2
b11010111 4
0'
#2175000
b100 9
b11 :
1'
#2180000
b101 2
b11101011 4
0'
#2185000
b101 9
b1 :
1'
#2190000
b110 2
b11110101 4
0'
#2195000
0!
b110 9
b0 :
1'
#2200000
b111 2
b1111010 4
0'
#2205000
b111 9
1'
#2210000
15
b0 2
b111101 4
0'
#2215000
0#
b0 9
1'
#2220000
05
1$
b111101 "
b111101 .
b111101 3
0'
#2221000
b10100 ,
#2225000
1'
#2230000
0$
0'
#2235000
1'
#2240000
1)
b11101101 *
b11101101 -
b11101101 6
0'
#2245000
1!
1#
b11101101 :
1'
#2246000
0)
#2250000
b1 2
b10011110 4
0'
#2255000
0!
b1 9
b1110110 :
1'
#2260000
b10 2
b1001111 4
0'
#2265000
1!
b10 9
b111011 :
1'
#2270000
b11 2
b10100111 4
0'
#2275000
b11 9
b11101 :
1'
#2280000
b100 2
b11010011 4
0'
#2285000
0!
b100 9
b1110 :
1'
#2290000
b101 2
b1101001 4
0'
#2295000
1!
b101 9
b111 :
1'
#2300000
b110 2
b10110100 4
0'
#2305000
b110 9
b11 :
1'
#2310000
b111 2
b11011010 4
0'
#2315000
b111 9
b1 :
1'
#2320000
15
b0 2
b11101101 4
0'
#2325000
0!
0#
b0 9
b0 :
1'
#2330000
05
1$
b11101101 "
b11101101 .
b11101101 3
0'
#2331000
b10101 ,
#2335000
1'
#2340000
0$
0'
#2345000
1'
#2350000
1)
b10001100 *
b10001100 -
b10001100 6
0'
